xia_cache/__init__.py
xia_cache/cache.cp310-win_amd64.pyd
xia_cache-0.1.7.dist-info/LICENSE.txt
xia_cache-0.1.7.dist-info/METADATA
xia_cache-0.1.7.dist-info/WHEEL
xia_cache-0.1.7.dist-info/top_level.txt
xia_cache-0.1.7.dist-info/RECORD
